setup.py
distributions_chethana/Binomialdistribution.py
distributions_chethana/Gaussiandistribution.py
distributions_chethana/Generaldistribution.py
distributions_chethana/__init__.py
distributions_chethana.egg-info/PKG-INFO
distributions_chethana.egg-info/SOURCES.txt
distributions_chethana.egg-info/dependency_links.txt
distributions_chethana.egg-info/not-zip-safe
distributions_chethana.egg-info/top_level.txt