Metadata-Version: 1.0
Name: distributions-chethana
Version: 0.12
Summary: Gaussian distributions
Home-page: UNKNOWN
Author: UNKNOWN
Author-email: UNKNOWN
License: UNKNOWN
Platform: UNKNOWN
